sinonym/__init__.py
sinonym/chinese_names_data.py
sinonym/detector.py
sinonym/ml_model_components.py
sinonym/resources.py
sinonym/coretypes/__init__.py
sinonym/coretypes/config.py
sinonym/coretypes/results.py
sinonym/data/README.md
sinonym/data/acl_2025_authors.txt
sinonym/data/chinese_japanese_classifier.joblib
sinonym/data/chinese_japanese_classifier.skops
sinonym/data/familyname_orcid.csv
sinonym/data/givenname_orcid.csv
sinonym/data/model_features.json
sinonym/patterns/__init__.py
sinonym/patterns/compiled_patterns.py
sinonym/patterns/regex_builders.py
sinonym/services/__init__.py
sinonym/services/batch_analysis.py
sinonym/services/cache.py
sinonym/services/ethnicity.py
sinonym/services/formatting.py
sinonym/services/initialization.py
sinonym/services/normalization.py
sinonym/services/parsing.py
sinonym/text_processing/__init__.py
sinonym/text_processing/compound_detector.py
sinonym/text_processing/text_normalizer.py
sinonym/text_processing/text_preprocessor.py
sinonym/utils/__init__.py
sinonym/utils/string_manipulation.py
sinonym/utils/thread_cache.py
sinonym-0.2.2.dist-info/METADATA
sinonym-0.2.2.dist-info/WHEEL
sinonym-0.2.2.dist-info/licenses/LICENSE
sinonym-0.2.2.dist-info/RECORD
