Metadata-Version: 2.4
Name: sinonym
Version: 0.2.2
Summary: Chinese Name Detection and Normalization Module
Project-URL: Homepage, https://github.com/allenai/sinonym
Project-URL: Repository, https://github.com/allenai/sinonym
Project-URL: Issues, https://github.com/allenai/sinonym/issues
Author-email: Sergey Feldman <sergey@allenai.org>
License: MIT
License-File: LICENSE
Keywords: chinese,names,nlp,pinyin,romanization
Classifier: Development Status :: 3 - Alpha
Classifier: Intended Audience :: Developers
Classifier: License :: OSI Approved :: MIT License
Classifier: Programming Language :: Python :: 3
Classifier: Programming Language :: Python :: 3.10
Classifier: Programming Language :: Python :: 3.11
Classifier: Programming Language :: Python :: 3.12
Classifier: Topic :: Software Development :: Libraries :: Python Modules
Classifier: Topic :: Text Processing :: Linguistic
Requires-Python: >=3.10
Requires-Dist: joblib>=1.3
Requires-Dist: numpy>=1.24
Requires-Dist: pypinyin>=0.44.0
Requires-Dist: requests>=2.31
Requires-Dist: scikit-learn<2,>=1.2
Requires-Dist: scipy>=1.10
Requires-Dist: skops>=0.9
Provides-Extra: dev
Requires-Dist: pytest-cov>=4.0.0; extra == 'dev'
Requires-Dist: pytest>=7.0.0; extra == 'dev'
Requires-Dist: ruff>=0.1.0; extra == 'dev'
Provides-Extra: test
Requires-Dist: pytest-cov>=4.0.0; extra == 'test'
Requires-Dist: pytest>=7.0.0; extra == 'test'
